net_analysis/__init__.py
net_analysis/net_analysis.py
net_analysis/net_analyzer.py
net_analysis/static/__init__.py
net_analysis/static/locales.json
net_analysis/static/static.py
net_analysis-1.0.1.dist-info/LICENSE
net_analysis-1.0.1.dist-info/METADATA
net_analysis-1.0.1.dist-info/WHEEL
net_analysis-1.0.1.dist-info/top_level.txt
net_analysis-1.0.1.dist-info/RECORD
