Metadata-Version: 2.1
Name: net-analysis
Version: 1.0.1
Summary: A package for analyze you IP and fetch additional information like ISP and LAT-LON, CITY, COUNTRY, etc
Author: Sina
Author-email: sinaorojlo53@gmail.com
Classifier: Programming Language :: Python :: 3
Classifier: License :: OSI Approved :: MIT License
Classifier: Operating System :: OS Independent
Requires-Python: >=3.6
License-File: LICENSE
Requires-Dist: countryinfo
Requires-Dist: loguru
Requires-Dist: requests
